{
	"configurations" : 
	[
		{
			"directories" : 
			[
				{
					"build" : ".",
					"jsonFile" : "directory-.-Debug-d0094a50bb2071803777.json",
					"minimumCMakeVersion" : 
					{
						"string" : "3.23"
					},
					"projectIndex" : 0,
					"source" : ".",
					"targetIndexes" : 
					[
						0
					]
				}
			],
			"name" : "Debug",
			"projects" : 
			[
				{
					"directoryIndexes" : 
					[
						0
					],
					"name" : "picture_editor",
					"targetIndexes" : 
					[
						0
					]
				}
			],
			"targets" : 
			[
				{
					"directoryIndex" : 0,
					"id" : "picture_editor::@6890427a1f51a3e7e1df",
					"jsonFile" : "target-picture_editor-Debug-10ef4190621fdb416a1c.json",
					"name" : "picture_editor",
					"projectIndex" : 0
				}
			]
		}
	],
	"kind" : "codemodel",
	"paths" : 
	{
		"build" : "D:/work/petC++/picture_editor/cmake-build-debug",
		"source" : "D:/work/petC++/picture_editor"
	},
	"version" : 
	{
		"major" : 2,
		"minor" : 4
	}
}
